{
  "9836134e-b892-4283-b6b2-78b5acf3ed45": {
    "asset": 1597390409304,
    "meta": 1597390409285,
    "relativePath": "effects"
  },
  "430eccbf-bf2c-4e6e-8c0c-884bbb487f32": {
    "asset": 1597390409296,
    "meta": 1597626480980,
    "relativePath": "effects\\__builtin-editor-gizmo-line.effect"
  },
  "6c5cf6e1-b044-4eac-9431-835644d57381": {
    "asset": 1597390409300,
    "meta": 1597626480996,
    "relativePath": "effects\\__builtin-editor-gizmo-unlit.effect"
  },
  "115286d1-2e10-49ee-aab4-341583f607e8": {
    "asset": 1597390409303,
    "meta": 1597626481047,
    "relativePath": "effects\\__builtin-editor-gizmo.effect"
  },
  "abc2cb62-7852-4525-a90d-d474487b88f2": {
    "asset": 1597390409287,
    "meta": 1597626481126,
    "relativePath": "effects\\builtin-phong.effect"
  },
  "e2f00085-c597-422d-9759-52c360279106": {
    "asset": 1597390409291,
    "meta": 1597626481173,
    "relativePath": "effects\\builtin-toon.effect"
  },
  "f8e6b000-5643-4b86-9080-aa680ce1f599": {
    "asset": 1597390409377,
    "meta": 1597390409308,
    "relativePath": "image"
  },
  "71561142-4c83-4933-afca-cb7a17f67053": {
    "asset": 1597390409313,
    "meta": 1597626481206,
    "relativePath": "image\\default_btn_disabled.png"
  },
  "e851e89b-faa2-4484-bea6-5c01dd9f06e2": {
    "asset": 1597390409315,
    "meta": 1597626481206,
    "relativePath": "image\\default_btn_normal.png"
  },
  "b43ff3c2-02bb-4874-81f7-f2dea6970f18": {
    "asset": 1597390409320,
    "meta": 1597626481228,
    "relativePath": "image\\default_btn_pressed.png"
  },
  "edd215b9-2796-4a05-aaf5-81f96c9281ce": {
    "asset": 1597390409323,
    "meta": 1597626481228,
    "relativePath": "image\\default_editbox_bg.png"
  },
  "d81ec8ad-247c-4e62-aa3c-d35c4193c7af": {
    "asset": 1597390409327,
    "meta": 1597626481249,
    "relativePath": "image\\default_panel.png"
  },
  "99170b0b-d210-46f1-b213-7d9e3f23098a": {
    "asset": 1597390409333,
    "meta": 1597626481251,
    "relativePath": "image\\default_progressbar_bg.png"
  },
  "567dcd80-8bf4-4535-8a5a-313f1caf078a": {
    "asset": 1597390409337,
    "meta": 1597626481267,
    "relativePath": "image\\default_radio_button_off.png"
  },
  "cfef78f1-c8df-49b7-8ed0-4c953ace2621": {
    "asset": 1597390409330,
    "meta": 1597626481265,
    "relativePath": "image\\default_progressbar.png"
  },
  "9d60001f-b5f4-4726-a629-2659e3ded0b8": {
    "asset": 1597390409340,
    "meta": 1597626481283,
    "relativePath": "image\\default_radio_button_on.png"
  },
  "4bab67cb-18e6-4099-b840-355f0473f890": {
    "asset": 1597390409347,
    "meta": 1597626481283,
    "relativePath": "image\\default_scrollbar_bg.png"
  },
  "d6d3ca85-4681-47c1-b5dd-d036a9d39ea2": {
    "asset": 1597390409351,
    "meta": 1597626481301,
    "relativePath": "image\\default_scrollbar_vertical.png"
  },
  "617323dd-11f4-4dd3-8eec-0caf6b3b45b9": {
    "asset": 1597390409354,
    "meta": 1597626481301,
    "relativePath": "image\\default_scrollbar_vertical_bg.png"
  },
  "0291c134-b3da-4098-b7b5-e397edbe947f": {
    "asset": 1597390409344,
    "meta": 1597626481318,
    "relativePath": "image\\default_scrollbar.png"
  },
  "0275e94c-56a7-410f-bd1a-fc7483f7d14a": {
    "asset": 1597390409362,
    "meta": 1597626481318,
    "relativePath": "image\\default_sprite_splash.png"
  },
  "6e056173-d285-473c-b206-40a7fff5386e": {
    "asset": 1597390409358,
    "meta": 1597626481335,
    "relativePath": "image\\default_sprite.png"
  },
  "73a0903d-d80e-4e3c-aa67-f999543c08f5": {
    "asset": 1597390409365,
    "meta": 1597626481335,
    "relativePath": "image\\default_toggle_checkmark.png"
  },
  "c25b9d50-c8fc-4d27-beeb-6e7c1f2e5c0f": {
    "asset": 1597390409370,
    "meta": 1597626481353,
    "relativePath": "image\\default_toggle_disabled.png"
  },
  "d29077ba-1627-4a72-9579-7b56a235340c": {
    "asset": 1597390409373,
    "meta": 1597626481353,
    "relativePath": "image\\default_toggle_normal.png"
  },
  "b181c1e4-0a72-4a91-bfb0-ae6f36ca60bd": {
    "asset": 1597390409377,
    "meta": 1597626481369,
    "relativePath": "image\\default_toggle_pressed.png"
  },
  "5c3eedba-6c41-4c0c-9ba7-d91f813cbd1c": {
    "asset": 1597390409383,
    "meta": 1597390409381,
    "relativePath": "materials"
  },
  "c4480a0a-6ac5-443f-8b40-361a14257fc8": {
    "asset": 1597390484463,
    "meta": 1597626481910,
    "relativePath": "materials\\builtin-phong.mtl"
  },
  "fc09f9bd-2cce-4605-b630-8145ef809ed6": {
    "asset": 1597390409396,
    "meta": 1597390409388,
    "relativePath": "misc"
  },
  "600301aa-3357-4a10-b086-84f011fa32ba": {
    "asset": 1597390409309,
    "meta": 1597626481369,
    "relativePath": "image\\default-particle.png"
  },
  "db019bf7-f71c-4111-98cf-918ea180cb48": {
    "asset": 1597390409458,
    "meta": 1597390409400,
    "relativePath": "model"
  },
  "e39e96e6-6f6e-413f-bcf1-ac7679bb648a": {
    "asset": 1597390409450,
    "meta": 1597390409403,
    "relativePath": "model\\prefab"
  },
  "a87cc147-01b2-43f8-8e42-a7ca90b0c757": {
    "asset": 1597390409404,
    "meta": 1597626481387,
    "relativePath": "model\\prefab\\box.prefab"
  },
  "fe1417b6-fe6b-46a4-ae7c-9fd331f33a2a": {
    "asset": 1597390409408,
    "meta": 1597626481389,
    "relativePath": "model\\prefab\\capsule.prefab"
  },
  "2be36297-9abb-4fee-8049-9ed5e271da8a": {
    "asset": 1597390409394,
    "meta": 1597626481369,
    "relativePath": "misc\\default_video.mp4"
  },
  "b5fc2cf2-7942-483d-be1f-bbeadc4714ad": {
    "asset": 1597390409411,
    "meta": 1597626481392,
    "relativePath": "model\\prefab\\cone.prefab"
  },
  "1c5e4038-953a-44c2-b620-0bbfc6170477": {
    "asset": 1597390409426,
    "meta": 1597626481398,
    "relativePath": "model\\prefab\\cylinder.prefab"
  },
  "3f376125-a699-40ca-ad05-04d662eaa1f2": {
    "asset": 1597390409434,
    "meta": 1597626481401,
    "relativePath": "model\\prefab\\plane.prefab"
  },
  "6c9ef10d-b479-420b-bfe6-39cdda6a8ae0": {
    "asset": 1597390409442,
    "meta": 1597626481403,
    "relativePath": "model\\prefab\\quad.prefab"
  },
  "2d9a4b85-b0ab-4c46-84c5-18f393ab2058": {
    "asset": 1597390409447,
    "meta": 1597626481407,
    "relativePath": "model\\prefab\\sphere.prefab"
  },
  "de510076-056b-484f-b94c-83bef217d0e1": {
    "asset": 1597390409450,
    "meta": 1597626481473,
    "relativePath": "model\\prefab\\torus.prefab"
  },
  "f6e6dd15-71d1-4ffe-ace7-24fd39942c05": {
    "asset": 1597390409469,
    "meta": 1597390409462,
    "relativePath": "obsolete"
  },
  "8a96b965-2dc0-4e03-aa90-3b79cb93b5b4": {
    "asset": 1597390409469,
    "meta": 1597626481495,
    "relativePath": "obsolete\\atom.png"
  },
  "f743d2b6-b7ea-4c14-a55b-547ed4d0a045": {
    "asset": 1597390409481,
    "meta": 1597390409473,
    "relativePath": "particle"
  },
  "b8223619-7e38-47c4-841f-9160c232495a": {
    "asset": 1597390409465,
    "meta": 1597626481930,
    "relativePath": "obsolete\\atom.plist"
  },
  "d0a82d39-bede-46c4-b698-c81ff0dedfff": {
    "asset": 1597390409480,
    "meta": 1597626481512,
    "relativePath": "particle\\atom.png"
  },
  "ae6c6c98-11e4-452f-8758-75f5c6a56e83": {
    "asset": 1597390409775,
    "meta": 1597390409486,
    "relativePath": "prefab"
  },
  "897ef7a1-4860-4f64-968d-f5924b18668a": {
    "asset": 1597390409488,
    "meta": 1597626481516,
    "relativePath": "prefab\\2d-camera.prefab"
  },
  "70d7cdb0-04cd-41bb-9480-c06a4785f386": {
    "asset": 1597390409492,
    "meta": 1597626481519,
    "relativePath": "prefab\\3d-camera.prefab"
  },
  "b2687ac4-099e-403c-a192-ff477686f4f5": {
    "asset": 1597390409476,
    "meta": 1597626481934,
    "relativePath": "particle\\atom.plist"
  },
  "70bbeb73-6dc2-4ee4-8faf-76b3a0e34ec4": {
    "asset": 1597390409495,
    "meta": 1597626481524,
    "relativePath": "prefab\\3d-particle.prefab"
  },
  "ed88f13d-fcad-4848-aa35-65a2cb973584": {
    "asset": 1597390409563,
    "meta": 1597626481527,
    "relativePath": "prefab\\3d-stage.prefab"
  },
  "972b9a4d-47ee-4c74-b5c3-61d8a69bc29f": {
    "asset": 1597390409566,
    "meta": 1597626481530,
    "relativePath": "prefab\\button.prefab"
  },
  "2c937608-2562-40ea-b264-7395df6f0cea": {
    "asset": 1597390409569,
    "meta": 1597626481533,
    "relativePath": "prefab\\canvas.prefab"
  },
  "61aeb05b-3b32-452b-8eed-2b76deeed554": {
    "asset": 1597390409572,
    "meta": 1597626481537,
    "relativePath": "prefab\\editbox.prefab"
  },
  "27756ebb-3d33-44b0-9b96-e858fadd4dd4": {
    "asset": 1597390409574,
    "meta": 1597626481540,
    "relativePath": "prefab\\label.prefab"
  },
  "785a442c-3ceb-45be-a46e-7317f625f3b9": {
    "asset": 1597390409577,
    "meta": 1597626481542,
    "relativePath": "prefab\\layout.prefab"
  },
  "a3ee0214-b432-4865-9666-4a3211814282": {
    "asset": 1597390409653,
    "meta": 1597390409581,
    "relativePath": "prefab\\light"
  },
  "61906da3-7003-4bda-9abc-5769c76faee4": {
    "asset": 1597390409582,
    "meta": 1597626481546,
    "relativePath": "prefab\\light\\ambient.prefab"
  },
  "ddb99b39-7004-47cd-9705-751905c43c46": {
    "asset": 1597390409585,
    "meta": 1597626481549,
    "relativePath": "prefab\\light\\directional.prefab"
  },
  "0cf30284-9073-46bc-9eba-e62b69dbbff3": {
    "asset": 1597390409588,
    "meta": 1597626481553,
    "relativePath": "prefab\\light\\point.prefab"
  },
  "f5331fd2-bf42-4ee3-a3fd-3e1657600eff": {
    "asset": 1597390409651,
    "meta": 1597626481556,
    "relativePath": "prefab\\light\\spot.prefab"
  },
  "ca8401fe-ad6e-41a8-bd46-8e3e4e9945be": {
    "asset": 1597390409656,
    "meta": 1597626481560,
    "relativePath": "prefab\\pageview.prefab"
  },
  "cd33edea-55f5-46c2-958d-357a01384a36": {
    "asset": 1597390409659,
    "meta": 1597626481563,
    "relativePath": "prefab\\particlesystem.prefab"
  },
  "5965ffac-69da-4b55-bcde-9225d0613c28": {
    "asset": 1597390409662,
    "meta": 1597626481567,
    "relativePath": "prefab\\progressBar.prefab"
  },
  "4a37dd57-78cd-4cec-aad4-f11a73d12b63": {
    "asset": 1597390409664,
    "meta": 1597626481571,
    "relativePath": "prefab\\richtext.prefab"
  },
  "32044bd2-481f-4cf1-a656-e2b2fb1594eb": {
    "asset": 1597390409666,
    "meta": 1597626481579,
    "relativePath": "prefab\\scrollview.prefab"
  },
  "0004d1cf-a0ad-47d8-ab17-34d3db9d35a3": {
    "asset": 1597390409668,
    "meta": 1597626481583,
    "relativePath": "prefab\\slider.prefab"
  },
  "1f55e3be-b89b-4b79-88de-47fd31018044": {
    "asset": 1597390409755,
    "meta": 1597626481586,
    "relativePath": "prefab\\sprite_splash.prefab"
  },
  "96083d03-c332-4a3f-9386-d03e2d19e8ee": {
    "asset": 1597390409671,
    "meta": 1597626481589,
    "relativePath": "prefab\\sprite.prefab"
  },
  "7de03a80-4457-438d-95a7-3e7cdffd6086": {
    "asset": 1597390409760,
    "meta": 1597626481592,
    "relativePath": "prefab\\tiledmap.prefab"
  },
  "0e42ba95-1fa1-46aa-b2cf-143cd1bcee2c": {
    "asset": 1597390409762,
    "meta": 1597626481603,
    "relativePath": "prefab\\tiledtile.prefab"
  },
  "0d784963-d024-4ea6-a7db-03be0ad63010": {
    "asset": 1597390409765,
    "meta": 1597626481622,
    "relativePath": "prefab\\toggle.prefab"
  },
  "bf0a434c-84dd-4a8e-a08a-7a36f180cc75": {
    "asset": 1597390409767,
    "meta": 1597626481622,
    "relativePath": "prefab\\toggleContainer.prefab"
  },
  "d1b8be49-b0a0-435c-83b7-552bed4bbe35": {
    "asset": 1597390409770,
    "meta": 1597626481654,
    "relativePath": "prefab\\toggleGroup.prefab"
  },
  "232d2782-c4bd-4bb4-9e01-909f03d6d3b9": {
    "asset": 1597390409772,
    "meta": 1597626481654,
    "relativePath": "prefab\\videoplayer.prefab"
  },
  "8c5001fd-07ee-4a4b-a8a0-63e15195e94d": {
    "asset": 1597390409775,
    "meta": 1597626481654,
    "relativePath": "prefab\\webview.prefab"
  },
  "d8afc78c-4eac-4a9f-83dd-67bc70344d33": {
    "asset": 1597390409876,
    "meta": 1597390409778,
    "relativePath": "resources"
  },
  "294c1663-4adf-4a1e-a795-53808011a38a": {
    "asset": 1597390409872,
    "meta": 1597390409780,
    "relativePath": "resources\\effects"
  },
  "144c3297-af63-49e8-b8ef-1cfa29b3be28": {
    "asset": 1597390409781,
    "meta": 1597626481670,
    "relativePath": "resources\\effects\\builtin-2d-gray-sprite.effect"
  },
  "0e93aeaa-0b53-4e40-b8e0-6268b4e07bd7": {
    "asset": 1597390409784,
    "meta": 1597626481686,
    "relativePath": "resources\\effects\\builtin-2d-spine.effect"
  },
  "2874f8dd-416c-4440-81b7-555975426e93": {
    "asset": 1597390409811,
    "meta": 1597626481701,
    "relativePath": "resources\\effects\\builtin-2d-sprite.effect"
  },
  "829a282c-b049-4019-bd38-5ace8d8a6417": {
    "asset": 1597390409814,
    "meta": 1597626481795,
    "relativePath": "resources\\effects\\builtin-3d-particle.effect"
  },
  "2a7c0036-e0b3-4fe1-8998-89a54b8a2bec": {
    "asset": 1597390409817,
    "meta": 1597626481822,
    "relativePath": "resources\\effects\\builtin-3d-trail.effect"
  },
  "c0040c95-c57f-49cd-9cbc-12316b73d0d4": {
    "asset": 1597390409820,
    "meta": 1597626481844,
    "relativePath": "resources\\effects\\builtin-clear-stencil.effect"
  },
  "6d91e591-4ce0-465c-809f-610ec95019c6": {
    "asset": 1597390409872,
    "meta": 1597626481869,
    "relativePath": "resources\\effects\\builtin-unlit.effect"
  },
  "bbee2217-c261-49bd-a8ce-708d6bcc3500": {
    "asset": 1597390409896,
    "meta": 1597390409877,
    "relativePath": "resources\\materials"
  },
  "6f801092-0c37-4f30-89ef-c8d960825b36": {
    "asset": 1597390484565,
    "meta": 1597626481973,
    "relativePath": "resources\\materials\\builtin-2d-base.mtl"
  },
  "3a7bb79f-32fd-422e-ada2-96f518fed422": {
    "asset": 1597390484571,
    "meta": 1597626481974,
    "relativePath": "resources\\materials\\builtin-2d-gray-sprite.mtl"
  },
  "7afd064b-113f-480e-b793-8817d19f63c3": {
    "asset": 1597390484578,
    "meta": 1597626481976,
    "relativePath": "resources\\materials\\builtin-2d-spine.mtl"
  },
  "eca5d2f2-8ef6-41c2-bbe6-f9c79d09c432": {
    "asset": 1597390484584,
    "meta": 1597626481977,
    "relativePath": "resources\\materials\\builtin-2d-sprite.mtl"
  },
  "466d4f9b-e5f4-4ea8-85d5-3c6e9a65658a": {
    "asset": 1597390409891,
    "meta": 1597626481981,
    "relativePath": "resources\\materials\\builtin-3d-trail.mtl"
  },
  "432fa09c-cf03-4cff-a186-982604408a07": {
    "asset": 1597390409888,
    "meta": 1597626481979,
    "relativePath": "resources\\materials\\builtin-3d-particle.mtl"
  },
  "cf7e0bb8-a81c-44a9-ad79-d28d43991032": {
    "asset": 1597390484594,
    "meta": 1597626481982,
    "relativePath": "resources\\materials\\builtin-clear-stencil.mtl"
  },
  "2a296057-247c-4a1c-bbeb-0548b6c98650": {
    "asset": 1597390484600,
    "meta": 1597626481983,
    "relativePath": "resources\\materials\\builtin-unlit.mtl"
  },
  "954fec8b-cd16-4bb9-a3b7-7719660e7558": {
    "asset": 1597390409457,
    "meta": 1597626484342,
    "relativePath": "model\\primitives.fbx"
  },
  "3104dda6-5877-4f44-b575-9aef4f40ff22": {
    "asset": 1597560060389,
    "meta": 1597559978379,
    "relativePath": "audio"
  },
  "b2b11971-337b-4f6f-a89c-4fbfe7d188ec": {
    "asset": 1597559978319,
    "meta": 1597560144265,
    "relativePath": "audio\\jump.mp3"
  },
  "9de55d86-73ce-425a-b1de-53300e5ba28e": {
    "asset": 1597559978321,
    "meta": 1597560144261,
    "relativePath": "audio\\score.mp3"
  },
  "78423ca8-9998-49a6-b13d-b9ae935a1fa4": {
    "asset": 1597560060408,
    "meta": 1597559978382,
    "relativePath": "migration"
  },
  "9b4405f2-6b38-40f3-8662-a66210d72ed2": {
    "asset": 1597559978317,
    "meta": 1597560144354,
    "relativePath": "migration\\use_v2.0.x_cc.Toggle_event.js"
  },
  "880f089c-d64f-4959-8927-4bb53a74ed80": {
    "asset": 1597559978382,
    "meta": 1597560145161,
    "relativePath": "mikado_outline_shadow.fnt"
  },
  "0b9c76e0-2054-4eea-a6d9-040d0aa037f0": {
    "asset": 1597626533515,
    "meta": 1597626533532,
    "relativePath": "game.fire"
  },
  "e00abb4e-4c93-4029-8e30-e91c1503802d": {
    "asset": 1597559978388,
    "meta": 1597560144372,
    "relativePath": "score_pop.anim"
  },
  "c47a9f4f-d5a5-40cc-9d19-6759f12e73cc": {
    "asset": 1597560218465,
    "meta": 1597560218476,
    "relativePath": "scoreFX.prefab"
  },
  "728cd57b-8823-4ba3-8262-cb69dd663824": {
    "asset": 1597560060469,
    "meta": 1597559978389,
    "relativePath": "scripts"
  },
  "0486f3aa-1eb2-4dfb-a739-3d083914787d": {
    "asset": 1597559978304,
    "meta": 1597560144632,
    "relativePath": "scripts\\Game.js"
  },
  "c10bb3dd-1988-4359-a2e8-28b577f1b1df": {
    "asset": 1597559978307,
    "meta": 1597560144829,
    "relativePath": "scripts\\Player.js"
  },
  "b1f9ef3c-6077-46af-ba83-d7bb21b6bdb0": {
    "asset": 1597559978308,
    "meta": 1597560144847,
    "relativePath": "scripts\\ScoreAnim.js"
  },
  "dd18cebb-a6bf-4e33-9c09-6ffc98e8e9df": {
    "asset": 1597559978312,
    "meta": 1597560144867,
    "relativePath": "scripts\\ScoreFX.js"
  },
  "218905eb-e110-4996-a4c9-8665c9fdfe6c": {
    "asset": 1597559978313,
    "meta": 1597560144906,
    "relativePath": "scripts\\Star.js"
  },
  "5dab09ec-e715-4118-aa4c-1edcd503aacf": {
    "asset": 1597559978384,
    "meta": 1597560144924,
    "relativePath": "mikado_outline_shadow.png"
  },
  "ec71375a-5bb7-4eec-96a4-758ff44844e3": {
    "asset": 1597560060548,
    "meta": 1597559978392,
    "relativePath": "textures"
  },
  "8ff27be6-af39-49d6-9ba1-e6e11d99c32f": {
    "asset": 1597559978390,
    "meta": 1597560144933,
    "relativePath": "Star.prefab"
  },
  "5e88959c-402e-422b-ad45-506b8cc96e08": {
    "asset": 1597559978395,
    "meta": 1597560144974,
    "relativePath": "textures\\btn_play.png"
  },
  "d44bfbd2-3386-414c-b1e5-59c64c114ea5": {
    "asset": 1597560060612,
    "meta": 1597559978397,
    "relativePath": "textures\\fx"
  },
  "4006dab6-bda9-4a73-8bf2-dafc42d68f61": {
    "asset": 1597559978393,
    "meta": 1597560144981,
    "relativePath": "textures\\background.jpg"
  },
  "95e8f80f-c673-41f0-a95f-b2086073abaa": {
    "asset": 1597559978293,
    "meta": 1597560145006,
    "relativePath": "textures\\fx\\fx_coinxiaosh_01.png"
  },
  "be591592-b0b8-40b0-8ff2-30ff156f2ef7": {
    "asset": 1597559978291,
    "meta": 1597560145010,
    "relativePath": "textures\\fx\\fx_coinxiaosh_00.png"
  },
  "3288de19-973d-4800-837f-ee3cb9395c42": {
    "asset": 1597559978295,
    "meta": 1597560145034,
    "relativePath": "textures\\fx\\fx_coinxiaosh_02.png"
  },
  "f3044bbc-3bd8-4b7c-bde2-a752bee30150": {
    "asset": 1597559978298,
    "meta": 1597560145038,
    "relativePath": "textures\\fx\\fx_coinxiaosh_03.png"
  },
  "f9c82bbd-99fe-4c20-9fee-531155aa9a2c": {
    "asset": 1597559978299,
    "meta": 1597560145062,
    "relativePath": "textures\\fx\\fx_coinxiaosh_04.png"
  },
  "3033f04a-c65e-45df-965c-03b07c5abfb0": {
    "asset": 1597559978302,
    "meta": 1597560145066,
    "relativePath": "textures\\fx\\fx_coinxiaosh_05.png"
  },
  "20a949c1-6ec4-4641-85d0-e1d05bc5d358": {
    "asset": 1597559978399,
    "meta": 1597560145106,
    "relativePath": "textures\\PurpleMonster.png"
  },
  "4f66ccd7-aed7-4db8-9490-d47cded1e2cd": {
    "asset": 1597559978397,
    "meta": 1597560145098,
    "relativePath": "textures\\ground.png"
  },
  "f3972116-ff71-4ea0-8e87-fa3d4c9f9c29": {
    "asset": 1597559978288,
    "meta": 1597560145147,
    "relativePath": "textures\\star.png"
  }
}